{
  "dealers": [
    {
      "id": "ee56c306-cc40-4dd9-8e86-ef11b313455a",
      "email": "joemachado62@live.com",
      "passwordHash": "$2b$12$ZGXYRdrN2iV6PPaR2zscB.dTwFE/9Ts9DX4JlAVE6kFRDw5j50PWu",
      "dealerName": "MJM Motors",
      "contactName": "Joe Machado",
      "phone": "(239) 888-1606",
      "address": "2748 Lambay Court, Cape Coral, Fl. 33991",
      "dealerLicenseNumber": "VI 7587965",
      "finNumber": "45-7587467",
      "subscriptionTier": "basic",
      "status": "active",
      "createdAt": "2025-06-30T12:03:39.121Z",
      "lastLogin": "2025-07-16T00:04:44.824Z",
      "failedLoginAttempts": 0,
      "accountLockedUntil": null,
      "emailVerified": false,
      "ghlUserId": null,
      "ghlContactId": null,
      "ghlIntegrationEnabled": false,
      "updatedAt": "2025-07-16T02:39:58.303Z",
      "profilePictureUrl": "uploads/profile-pictures/ee56c306-cc40-4dd9-8e86-ef11b313455a-1752633598296.jpg"
    }
  ],
  "lastUpdated": "2025-07-16T02:43:00.000Z"
}